README.rst
setup.py
pyfinite/__init__.py
pyfinite/ffield.py
pyfinite/file_ecc.py
pyfinite/genericmatrix.py
pyfinite/rs_code.py
pyfinite/test_basics.py
pyfinite.egg-info/PKG-INFO
pyfinite.egg-info/SOURCES.txt
pyfinite.egg-info/dependency_links.txt
pyfinite.egg-info/entry_points.txt
pyfinite.egg-info/requires.txt
pyfinite.egg-info/top_level.txt