Metadata-Version: 1.1
Name: pyfinite
Version: 1.9
Summary: Finite field operations and erasure correction codes.
Home-page: http://github.com/emin63/pyfinite
Author: Emin Martinian
Author-email: emin.martinian@gmail.com
License: MIT
Keywords: finite field math
Platform: UNKNOWN
Classifier: Development Status :: 3 - Alpha
Classifier: Intended Audience :: Developers
Classifier: Programming Language :: Python :: 3
